gitlabagent/__init__.py
gitlabagent/base.py
gitlabagent/webhookobject.py
gitlab_agent-0.0.2.dist-info/LICENSE
gitlab_agent-0.0.2.dist-info/METADATA
gitlab_agent-0.0.2.dist-info/WHEEL
gitlab_agent-0.0.2.dist-info/top_level.txt
gitlab_agent-0.0.2.dist-info/RECORD
