Metadata-Version: 2.1
Name: gitlab-agent
Version: 0.0.2
Summary: A wrapper to use gitlab webhooks
Home-page: https://github.com/reevoremo/gitlab-agent
Author: Behan Remoshan BENET RUBAN
Author-email: b.remoshan@gmail.com
License: UNKNOWN
Platform: UNKNOWN
Classifier: Programming Language :: Python :: 3
Classifier: License :: OSI Approved :: MIT License
Classifier: Operating System :: OS Independent
Requires-Python: >=3.6
